melopero_amg8833/AMG8833.py
melopero_amg8833/__init__.py
melopero_amg8833-0.1.5.dist-info/METADATA
melopero_amg8833-0.1.5.dist-info/RECORD
melopero_amg8833-0.1.5.dist-info/WHEEL
melopero_amg8833-0.1.5.dist-info/top_level.txt
