Metadata-Version: 2.1
Name: melopero-amg8833
Version: 0.1.5
Summary: A module to easily access Melopero's AMG8833 sensor's features
Home-page: https://github.com/melopero/Melopero_AMG8833/tree/master/module
Author: Melopero
Author-email: info@melopero.com
License: MIT
Platform: UNKNOWN
Classifier: Development Status :: 3 - Alpha
Classifier: License :: OSI Approved :: MIT License
Classifier: Programming Language :: Python :: 3
Classifier: Programming Language :: Python :: 3.5
Requires-Dist: smbus2
